flask_fas.py
python_fedora-0.3.32.3.dist-info/RECORD
python_fedora-0.3.32.3.dist-info/WHEEL
python_fedora-0.3.32.3.dist-info/pydist.json
python_fedora-0.3.32.3.dist-info/DESCRIPTION.rst
python_fedora-0.3.32.3.dist-info/METADATA
python_fedora-0.3.32.3.dist-info/entry_points.txt
python_fedora-0.3.32.3.dist-info/top_level.txt
fedora/__init__.py
fedora/textutils.py
fedora/release.py
fedora/urlutils.py
fedora/iterutils.py
fedora/django/__init__.py
fedora/django/auth/__init__.py
fedora/django/auth/models.py
fedora/django/auth/backends.py
fedora/django/auth/middleware.py
fedora/django/auth/management/__init__.py
fedora/wsgi/__init__.py
fedora/wsgi/csrf.py
fedora/wsgi/test/__init__.py
fedora/wsgi/test/websetup.py
fedora/wsgi/test/testapp.py
fedora/wsgi/test/test_csrf.py
fedora/wsgi/test/config/app_cfg.py
fedora/wsgi/test/config/__init__.py
fedora/wsgi/test/config/environment.py
fedora/wsgi/test/templates/__init__.py
fedora/wsgi/test/lib/__init__.py
fedora/wsgi/test/lib/app_globals.py
fedora/wsgi/test/lib/base.py
fedora/wsgi/test/lib/helpers.py
fedora/wsgi/test/model/__init__.py
fedora/wsgi/test/model/auth.py
fedora/wsgi/test/controllers/__init__.py
fedora/wsgi/test/controllers/root.py
fedora/wsgi/faswho/__init__.py
fedora/wsgi/faswho/faswhoplugin.py
fedora/compat25/__init__.py
fedora/tg2/__init__.py
fedora/tg2/utils.py
fedora/tg2/templates/__init__.py
fedora/tg2/templates/mako/__init__.py
fedora/tg2/templates/mako/jsglobals.mak
fedora/tg2/templates/mako/login.mak
fedora/tg2/templates/genshi/__init__.py
fedora/tg2/templates/genshi/jsglobals.html
fedora/tg2/templates/genshi/login.html
fedora/client/__init__.py
fedora/client/fas2.py
fedora/client/bodhi.py
fedora/client/wiki.py
fedora/client/proxyclient.py
fedora/client/baseclient.py
fedora/client/pkgdb.py
fedora/client/fasproxy.py
fedora/tg/__init__.py
fedora/tg/controllers.py
fedora/tg/client.py
fedora/tg/tg1utils.py
fedora/tg/json.py
fedora/tg/tg2utils.py
fedora/tg/util.py
fedora/tg/utils.py
fedora/tg/widgets.py
fedora/tg/templates/__init__.py
fedora/tg/templates/genshi/__init__.py
fedora/tg/templates/genshi/jsglobals.html
fedora/tg/templates/genshi/login.html
fedora/tg/identity/__init__.py
fedora/tg/identity/soprovidercsrf.py
fedora/tg/identity/jsonfasprovider1.py
