Metadata-Version: 2.0
Name: python-fedora
Version: 0.3.32.3
Summary: Python modules for interacting with Fedora Services
Home-page: https://fedorahosted.org/python-fedora
Author: Toshio Kuratomi, Luke Macken, Ricky Elrod
Author-email: tkuratom@redhat.com
License: LGPLv2+
Download-URL: https://fedorahosted.org/releases/p/y/python-fedora/
Keywords: Fedora Python Webservices
Platform: UNKNOWN
Classifier: Development Status :: 4 - Beta
Classifier: Framework :: TurboGears
Classifier: Framework :: Django
Classifier: Intended Audience :: Developers
Classifier: Intended Audience :: System Administrators
Classifier: License :: OSI Approved :: GNU Lesser General Public License v2 or later (LGPLv2+)
Classifier: Programming Language :: Python :: 2.5
Classifier: Programming Language :: Python :: 2.6
Classifier: Programming Language :: Python :: 2.7
Classifier: Topic :: Internet :: WWW/HTTP
Classifier: Topic :: Software Development :: Libraries :: Python Modules
Requires-Dist: bunch
Requires-Dist: kitchen
Requires-Dist: requests
Provides-Extra: flask
Requires-Dist: Flask; extra == 'flask'
Requires-Dist: Flask-WTF; extra == 'flask'
Provides-Extra: tg
Requires-Dist: TurboGears (>=1.0.4); extra == 'tg'
Requires-Dist: SQLAlchemy; extra == 'tg'
Requires-Dist: decorator; extra == 'tg'
Provides-Extra: wsgi
Requires-Dist: repoze.who; extra == 'wsgi'
Requires-Dist: Beaker; extra == 'wsgi'
Requires-Dist: Paste; extra == 'wsgi'
